smartwrap/__init__.py
smartwrap-0.0.2.dist-info/METADATA
smartwrap-0.0.2.dist-info/WHEEL
smartwrap-0.0.2.dist-info/top_level.txt
smartwrap-0.0.2.dist-info/RECORD
