Metadata-Version: 2.1
Name: smartwrap
Version: 0.0.2
Summary: A smart text wrapper
Author-email: Martin Bagic <martin.bagic@outlook.com>
Project-URL: Homepage, https://github.com/pypa/smartwrap
Classifier: Programming Language :: Python :: 3
Classifier: Operating System :: OS Independent
Requires-Python: >=3.8
